winunlock/__init__.py
winunlock/_iotype.py
winunlock/_monkeypatch.py
winunlock/_open.py
winunlock/py.typed
winunlock/version.py
winunlock-0.1.6.dist-info/LICENSE
winunlock-0.1.6.dist-info/METADATA
winunlock-0.1.6.dist-info/WHEEL
winunlock-0.1.6.dist-info/top_level.txt
winunlock-0.1.6.dist-info/RECORD
