Metadata-Version: 2.1
Name: winunlock
Version: 0.1.6
Summary: A Python module that provides functionality for opening certain types of locked files in Windows.
Home-page: https://github.com/autoactuary/winunlock
Author: Auto Actuary
Classifier: Programming Language :: Python :: 3
Classifier: License :: OSI Approved :: MIT License
Classifier: Operating System :: Microsoft :: Windows
Requires-Python: >=3.6
License-File: LICENSE
